{
  "$schema": "https://mintlify.com/docs.json",
  "name": "Deeztracker Mobile",
  "theme": "almond",
  "colors": {
    "primary": "#94cb04",
    "light": "#545454",
    "dark": "#94cb04"
  },
  "favicon": "https://media.brand.dev/288cc7c4-5cef-4376-950b-bdf0083eedae.png",
  "logo": {
    "light": "/logo.png",
    "dark": "/logo.png"
  },
  "navbar": {
    "primary": {
      "type": "github",
      "href": "https://github.com/xScherpschutter/Deeztracker-Mobile"
    }
  },
  "footer": {
    "socials": {
      "github": "https://github.com/xScherpschutter/Deeztracker-Mobile"
    }
  },
  "navigation": {
    "tabs": [
      {
        "tab": "Documentation",
        "groups": [
          {
            "group": "Get Started",
            "pages": [
              "introduction",
              "installation",
              "quickstart"
            ]
          },
          {
            "group": "Features",
            "pages": [
              "features/search-discovery",
              "features/download-management",
              "features/music-player",
              "features/lyrics",
              "features/playlists",
              "features/local-library"
            ]
          },
          {
            "group": "User Guide",
            "pages": [
              "guide/authentication",
              "guide/downloading-music",
              "guide/playing-music",
              "guide/managing-playlists",
              "guide/settings"
            ]
          },
          {
            "group": "Development",
            "pages": [
              "development/building",
              "development/architecture",
              "development/project-structure"
            ]
          }
        ]
      },
      {
        "tab": "API Reference",
        "groups": [
          {
            "group": "Core Services",
            "pages": [
              "api/rusteer-service",
              "api/download-manager",
              "api/player-controller"
            ]
          },
          {
            "group": "Data Models",
            "pages": [
              "api/models/track",
              "api/models/album",
              "api/models/playlist"
            ]
          },
          {
            "group": "UI Components",
            "pages": [
              "api/components/music-player",
              "api/components/track-list",
              "api/components/dialogs"
            ]
          }
        ]
      }
    ]
  }
}
